README.md
setup.cfg
setup.py
fist/__init__.py
fist/client.py
fistpy.egg-info/PKG-INFO
fistpy.egg-info/SOURCES.txt
fistpy.egg-info/dependency_links.txt
fistpy.egg-info/requires.txt
fistpy.egg-info/top_level.txt
tests/__init__.py
tests/conftest.py
tests/test_main.py